{
  "generatedAt": "2026-07-05T00:47:18.831600+02:00",
  "generatedAtHuman": "Sunday 05 July 2026 om 00:47",
  "periodLabel": "sinds ~1 week geleden",
  "changes": [
    {
      "ticker": "ASML",
      "daysAgo": 3,
      "changes": [
        {
          "type": "composite",
          "dir": "down",
          "text": "Composiet 66 ↓ 56"
        },
        {
          "type": "valuation",
          "dir": "neutral",
          "text": "Waardering: Aan de dure kant (PEG 2.5–3.5) → Duur (PEG > 3.5)"
        },
        {
          "type": "signal",
          "dir": "up",
          "text": "Signaal: NEUTRAAL → VERKOOP"
        },
        {
          "type": "rsi",
          "dir": "down",
          "text": "RSI weekly overbought (74)"
        }
      ]
    },
    {
      "ticker": "ASMI",
      "daysAgo": 3,
      "changes": [
        {
          "type": "valuation",
          "dir": "neutral",
          "text": "Waardering: Duur (PEG > 3.5) → Aan de dure kant (PEG 2.5–3.5)"
        },
        {
          "type": "signal",
          "dir": "neutral",
          "text": "Signaal: LICHT KOOP → NEUTRAAL"
        }
      ]
    },
    {
      "ticker": "GOOGL",
      "daysAgo": 3,
      "changes": [
        {
          "type": "composite",
          "dir": "down",
          "text": "Composiet 76 ↓ 69"
        },
        {
          "type": "valuation",
          "dir": "neutral",
          "text": "Waardering: Redelijk (PEG 1–1.5) → Aan de dure kant (PEG 2.5–3.5)"
        }
      ]
    },
    {
      "ticker": "LHX",
      "daysAgo": 3,
      "changes": [
        {
          "type": "composite",
          "dir": "up",
          "text": "Composiet 51 ↑ 56"
        },
        {
          "type": "valuation",
          "dir": "neutral",
          "text": "Waardering: Aan de dure kant (PEG 2.5–3.5) → Neutraal (PEG 1.5–2.5)"
        }
      ]
    },
    {
      "ticker": "MOGA",
      "daysAgo": 3,
      "changes": [
        {
          "type": "composite",
          "dir": "down",
          "text": "Composiet 54 ↓ 46"
        },
        {
          "type": "valuation",
          "dir": "neutral",
          "text": "Waardering: Neutraal (PEG 1.5–2.5) → Duur (PEG > 3.5)"
        }
      ]
    },
    {
      "ticker": "MU",
      "daysAgo": 3,
      "changes": [
        {
          "type": "signal",
          "dir": "neutral",
          "text": "Signaal: VERKOOP → LICHT KOOP"
        }
      ]
    },
    {
      "ticker": "AMZN",
      "daysAgo": 3,
      "changes": [
        {
          "type": "valuation",
          "dir": "neutral",
          "text": "Waardering: Neutraal (PEG 1.5–2.5) → Aan de dure kant (PEG 2.5–3.5)"
        }
      ]
    }
  ],
  "changedCount": 7,
  "note": "Toont enkel wat veranderde t.o.v. ~7 dagen geleden. Geen wijzigingen = stabiele week."
}