{
  "generatedAt": "2026-07-13T23:10:26.190457+02:00",
  "generatedAtHuman": "Monday 13 July 2026 om 23:10",
  "periodLabel": "sinds ~1 week geleden",
  "changes": [
    {
      "ticker": "ASML",
      "daysAgo": 7,
      "changes": [
        {
          "type": "composite",
          "dir": "up",
          "text": "Composiet 45 \u2191 59"
        },
        {
          "type": "valuation",
          "dir": "neutral",
          "text": "Waardering: Duur (PEG > 3.5) \u2192 Aan de dure kant (PEG 2.5\u20133.5)"
        },
        {
          "type": "signal",
          "dir": "up",
          "text": "Signaal: CAUTION (overextended) \u2192 VERKOOP"
        }
      ]
    },
    {
      "ticker": "LHX",
      "daysAgo": 7,
      "changes": [
        {
          "type": "composite",
          "dir": "down",
          "text": "Composiet 54 \u2193 34"
        },
        {
          "type": "valuation",
          "dir": "neutral",
          "text": "Waardering: Neutraal (PEG 1.5\u20132.5) \u2192 Duur (PEG > 3.5)"
        },
        {
          "type": "signal",
          "dir": "down",
          "text": "Signaal: KOOP \u2192 VERKOOP"
        }
      ]
    },
    {
      "ticker": "TDG",
      "daysAgo": 7,
      "changes": [
        {
          "type": "composite",
          "dir": "up",
          "text": "Composiet 51 \u2191 60"
        },
        {
          "type": "valuation",
          "dir": "neutral",
          "text": "Waardering: Aan de dure kant (PEG 2.5\u20133.5) \u2192 Neutraal (PEG 1.5\u20132.5)"
        },
        {
          "type": "signal",
          "dir": "down",
          "text": "Signaal: LICHT KOOP \u2192 STERK VERKOOP"
        }
      ]
    },
    {
      "ticker": "OPEN",
      "daysAgo": 7,
      "changes": [
        {
          "type": "composite",
          "dir": "up",
          "text": "Composiet 39 \u2191 44"
        },
        {
          "type": "signal",
          "dir": "neutral",
          "text": "Signaal: LICHT KOOP \u2192 KOOP"
        },
        {
          "type": "price",
          "dir": "down",
          "text": "Koers -12.6% deze week ($5\u2192$4)"
        }
      ]
    },
    {
      "ticker": "V",
      "daysAgo": 7,
      "changes": [
        {
          "type": "composite",
          "dir": "up",
          "text": "Composiet 54 \u2191 61"
        },
        {
          "type": "valuation",
          "dir": "neutral",
          "text": "Waardering: Aan de dure kant (PEG 2.5\u20133.5) \u2192 Neutraal (PEG 1.5\u20132.5)"
        },
        {
          "type": "signal",
          "dir": "neutral",
          "text": "Signaal: LICHT VERKOOP \u2192 VERKOOP"
        }
      ]
    },
    {
      "ticker": "NET",
      "daysAgo": 7,
      "changes": [
        {
          "type": "composite",
          "dir": "down",
          "text": "Composiet 38 \u2193 32"
        },
        {
          "type": "signal",
          "dir": "up",
          "text": "Signaal: CAUTION (overextended) \u2192 KOOP"
        },
        {
          "type": "price",
          "dir": "up",
          "text": "Koers +8.9% deze week ($247\u2192$270)"
        }
      ]
    },
    {
      "ticker": "AIR",
      "daysAgo": 7,
      "changes": [
        {
          "type": "composite",
          "dir": "down",
          "text": "Composiet 52 \u2193 41"
        },
        {
          "type": "valuation",
          "dir": "neutral",
          "text": "Waardering: Aan de dure kant (PEG 2.5\u20133.5) \u2192 Duur (PEG > 3.5)"
        },
        {
          "type": "signal",
          "dir": "up",
          "text": "Signaal: NEUTRAAL \u2192 LICHT KOOP"
        }
      ]
    },
    {
      "ticker": "HARMONIC",
      "daysAgo": 7,
      "changes": [
        {
          "type": "composite",
          "dir": "up",
          "text": "Composiet 36 \u2191 42"
        },
        {
          "type": "signal",
          "dir": "up",
          "text": "Signaal: CAUTION (overextended) \u2192 KOOP"
        },
        {
          "type": "price",
          "dir": "down",
          "text": "Koers -10.9% deze week ($8840\u2192$7880)"
        }
      ]
    },
    {
      "ticker": "RGTI",
      "daysAgo": 7,
      "changes": [
        {
          "type": "composite",
          "dir": "down",
          "text": "Composiet 50 \u2193 45"
        },
        {
          "type": "signal",
          "dir": "neutral",
          "text": "Signaal: LICHT VERKOOP \u2192 VERKOOP"
        },
        {
          "type": "price",
          "dir": "down",
          "text": "Koers -15.1% deze week ($18\u2192$15)"
        }
      ]
    },
    {
      "ticker": "GOOGL",
      "daysAgo": 7,
      "changes": [
        {
          "type": "valuation",
          "dir": "neutral",
          "text": "Waardering: Aan de dure kant (PEG 2.5\u20133.5) \u2192 Neutraal (PEG 1.5\u20132.5)"
        },
        {
          "type": "signal",
          "dir": "down",
          "text": "Signaal: KOOP \u2192 STERK VERKOOP"
        }
      ]
    },
    {
      "ticker": "ORCL",
      "daysAgo": 7,
      "changes": [
        {
          "type": "valuation",
          "dir": "neutral",
          "text": "Waardering: Neutraal (PEG 1.5\u20132.5) \u2192 Redelijk (PEG 1\u20131.5)"
        },
        {
          "type": "price",
          "dir": "down",
          "text": "Koers -8.8% deze week ($144\u2192$132)"
        }
      ]
    },
    {
      "ticker": "MOGA",
      "daysAgo": 7,
      "changes": [
        {
          "type": "composite",
          "dir": "up",
          "text": "Composiet 32 \u2191 37"
        },
        {
          "type": "signal",
          "dir": "up",
          "text": "Signaal: CAUTION (overextended) \u2192 STERK VERKOOP"
        }
      ]
    },
    {
      "ticker": "RKLB",
      "daysAgo": 7,
      "changes": [
        {
          "type": "signal",
          "dir": "up",
          "text": "Signaal: CAUTION (overextended) \u2192 VERKOOP"
        },
        {
          "type": "price",
          "dir": "down",
          "text": "Koers -17.9% deze week ($93\u2192$77)"
        }
      ]
    },
    {
      "ticker": "MNST",
      "daysAgo": 7,
      "changes": [
        {
          "type": "composite",
          "dir": "down",
          "text": "Composiet 46 \u2193 40"
        },
        {
          "type": "signal",
          "dir": "up",
          "text": "Signaal: CAUTION (overextended) \u2192 KOOP"
        }
      ]
    },
    {
      "ticker": "ADM",
      "daysAgo": 7,
      "changes": [
        {
          "type": "composite",
          "dir": "down",
          "text": "Composiet 67 \u2193 50"
        },
        {
          "type": "valuation",
          "dir": "neutral",
          "text": "Waardering: Neutraal (PEG 1.5\u20132.5) \u2192 Duur (PEG > 3.5)"
        }
      ]
    },
    {
      "ticker": "MELI",
      "daysAgo": 7,
      "changes": [
        {
          "type": "gate",
          "dir": "down",
          "text": "Uit kwaliteitspoort \u2717"
        },
        {
          "type": "valuation",
          "dir": "neutral",
          "text": "Waardering: Redelijk (PEG 1\u20131.5) \u2192 Aantrekkelijk (PEG < 1)"
        }
      ]
    },
    {
      "ticker": "CRWV",
      "daysAgo": 7,
      "changes": [
        {
          "type": "composite",
          "dir": "down",
          "text": "Composiet 45 \u2193 35"
        },
        {
          "type": "signal",
          "dir": "up",
          "text": "Signaal: NEUTRAAL \u2192 VERKOOP"
        }
      ]
    },
    {
      "ticker": "MSFT",
      "daysAgo": 7,
      "changes": [
        {
          "type": "composite",
          "dir": "down",
          "text": "Composiet 64 \u2193 56"
        },
        {
          "type": "signal",
          "dir": "neutral",
          "text": "Signaal: VERKOOP \u2192 CAUTION (overextended)"
        }
      ]
    },
    {
      "ticker": "NVDA",
      "daysAgo": 7,
      "changes": [
        {
          "type": "composite",
          "dir": "down",
          "text": "Composiet 74 \u2193 69"
        },
        {
          "type": "signal",
          "dir": "up",
          "text": "Signaal: NEUTRAAL \u2192 STERK VERKOOP"
        }
      ]
    },
    {
      "ticker": "ALFEN",
      "daysAgo": 7,
      "changes": [
        {
          "type": "valuation",
          "dir": "neutral",
          "text": "Waardering: Hoge P/E (absoluut) \u2192 Gemiddelde P/E (absoluut)"
        },
        {
          "type": "signal",
          "dir": "up",
          "text": "Signaal: CAUTION (overextended) \u2192 LICHT KOOP"
        }
      ]
    },
    {
      "ticker": "NFLX",
      "daysAgo": 7,
      "changes": [
        {
          "type": "composite",
          "dir": "down",
          "text": "Composiet 67 \u2193 61"
        },
        {
          "type": "valuation",
          "dir": "neutral",
          "text": "Waardering: Aantrekkelijk (PEG < 1) \u2192 Neutraal (PEG 1.5\u20132.5)"
        }
      ]
    },
    {
      "ticker": "BABA",
      "daysAgo": 7,
      "changes": [
        {
          "type": "composite",
          "dir": "down",
          "text": "Composiet 59 \u2193 52"
        },
        {
          "type": "price",
          "dir": "up",
          "text": "Koers +15.3% deze week ($97\u2192$112)"
        }
      ]
    },
    {
      "ticker": "TER",
      "daysAgo": 7,
      "changes": [
        {
          "type": "signal",
          "dir": "up",
          "text": "Signaal: CAUTION (overextended) \u2192 VERKOOP"
        },
        {
          "type": "price",
          "dir": "down",
          "text": "Koers -10.3% deze week ($380\u2192$341)"
        }
      ]
    },
    {
      "ticker": "CGNX",
      "daysAgo": 7,
      "changes": [
        {
          "type": "signal",
          "dir": "up",
          "text": "Signaal: CAUTION (overextended) \u2192 KOOP"
        },
        {
          "type": "price",
          "dir": "down",
          "text": "Koers -9.2% deze week ($70\u2192$64)"
        }
      ]
    },
    {
      "ticker": "NOVT",
      "daysAgo": 7,
      "changes": [
        {
          "type": "signal",
          "dir": "up",
          "text": "Signaal: CAUTION (overextended) \u2192 KOOP"
        },
        {
          "type": "price",
          "dir": "down",
          "text": "Koers -9.3% deze week ($165\u2192$150)"
        }
      ]
    },
    {
      "ticker": "PL",
      "daysAgo": 7,
      "changes": [
        {
          "type": "signal",
          "dir": "neutral",
          "text": "Signaal: KOOP \u2192 CAUTION (overextended)"
        },
        {
          "type": "price",
          "dir": "down",
          "text": "Koers -16.3% deze week ($31\u2192$26)"
        }
      ]
    },
    {
      "ticker": "WM",
      "daysAgo": 7,
      "changes": [
        {
          "type": "signal",
          "dir": "up",
          "text": "Signaal: NEUTRAAL \u2192 KOOP"
        }
      ]
    },
    {
      "ticker": "CAT",
      "daysAgo": 7,
      "changes": [
        {
          "type": "signal",
          "dir": "up",
          "text": "Signaal: CAUTION (overextended) \u2192 STERK VERKOOP"
        }
      ]
    },
    {
      "ticker": "ASMI",
      "daysAgo": 7,
      "changes": [
        {
          "type": "signal",
          "dir": "up",
          "text": "Signaal: CAUTION (overextended) \u2192 VERKOOP"
        }
      ]
    },
    {
      "ticker": "MU",
      "daysAgo": 7,
      "changes": [
        {
          "type": "signal",
          "dir": "up",
          "text": "Signaal: CAUTION (overextended) \u2192 STERK VERKOOP"
        }
      ]
    },
    {
      "ticker": "AMZN",
      "daysAgo": 7,
      "changes": [
        {
          "type": "valuation",
          "dir": "neutral",
          "text": "Waardering: Aan de dure kant (PEG 2.5\u20133.5) \u2192 Neutraal (PEG 1.5\u20132.5)"
        }
      ]
    },
    {
      "ticker": "KTOS",
      "daysAgo": 7,
      "changes": [
        {
          "type": "price",
          "dir": "down",
          "text": "Koers -12.9% deze week ($54\u2192$47)"
        }
      ]
    },
    {
      "ticker": "SDGR",
      "daysAgo": 7,
      "changes": [
        {
          "type": "signal",
          "dir": "up",
          "text": "Signaal: CAUTION (overextended) \u2192 LICHT KOOP"
        }
      ]
    },
    {
      "ticker": "BNGO",
      "daysAgo": 7,
      "changes": [
        {
          "type": "signal",
          "dir": "neutral",
          "text": "Signaal: LICHT KOOP \u2192 NEUTRAAL"
        }
      ]
    },
    {
      "ticker": "III",
      "daysAgo": 7,
      "changes": [
        {
          "type": "signal",
          "dir": "neutral",
          "text": "Signaal: VERKOOP \u2192 STERK VERKOOP"
        }
      ]
    },
    {
      "ticker": "SHOP",
      "daysAgo": 7,
      "changes": [
        {
          "type": "signal",
          "dir": "neutral",
          "text": "Signaal: LICHT VERKOOP \u2192 VERKOOP"
        }
      ]
    },
    {
      "ticker": "MTLS",
      "daysAgo": 7,
      "changes": [
        {
          "type": "signal",
          "dir": "up",
          "text": "Signaal: CAUTION (overextended) \u2192 KOOP"
        }
      ]
    },
    {
      "ticker": "SNAP",
      "daysAgo": 7,
      "changes": [
        {
          "type": "signal",
          "dir": "neutral",
          "text": "Signaal: LICHT KOOP \u2192 NEUTRAAL"
        }
      ]
    },
    {
      "ticker": "NKE",
      "daysAgo": 7,
      "changes": [
        {
          "type": "signal",
          "dir": "neutral",
          "text": "Signaal: LICHT VERKOOP \u2192 VERKOOP"
        }
      ]
    },
    {
      "ticker": "DIE",
      "daysAgo": 7,
      "changes": [
        {
          "type": "signal",
          "dir": "down",
          "text": "Signaal: LICHT KOOP \u2192 VERKOOP"
        }
      ]
    },
    {
      "ticker": "LOTB",
      "daysAgo": 7,
      "changes": [
        {
          "type": "signal",
          "dir": "up",
          "text": "Signaal: CAUTION (overextended) \u2192 KOOP"
        }
      ]
    },
    {
      "ticker": "MSTR",
      "daysAgo": 7,
      "changes": [
        {
          "type": "price",
          "dir": "down",
          "text": "Koers -9.4% deze week ($102\u2192$92)"
        }
      ]
    },
    {
      "ticker": "BLK",
      "daysAgo": 7,
      "changes": [
        {
          "type": "signal",
          "dir": "neutral",
          "text": "Signaal: STERK VERKOOP \u2192 CAUTION (overextended)"
        }
      ]
    },
    {
      "ticker": "KEYENCE",
      "daysAgo": 7,
      "changes": [
        {
          "type": "signal",
          "dir": "up",
          "text": "Signaal: CAUTION (overextended) \u2192 KOOP"
        }
      ]
    },
    {
      "ticker": "FANUC",
      "daysAgo": 7,
      "changes": [
        {
          "type": "signal",
          "dir": "down",
          "text": "Signaal: KOOP \u2192 VERKOOP"
        }
      ]
    },
    {
      "ticker": "YASKAWA",
      "daysAgo": 7,
      "changes": [
        {
          "type": "signal",
          "dir": "up",
          "text": "Signaal: CAUTION (overextended) \u2192 KOOP"
        }
      ]
    },
    {
      "ticker": "SOFTBANK",
      "daysAgo": 7,
      "changes": [
        {
          "type": "signal",
          "dir": "down",
          "text": "Signaal: KOOP \u2192 STERK VERKOOP"
        }
      ]
    },
    {
      "ticker": "ROK",
      "daysAgo": 7,
      "changes": [
        {
          "type": "signal",
          "dir": "up",
          "text": "Signaal: CAUTION (overextended) \u2192 KOOP"
        }
      ]
    },
    {
      "ticker": "IONQ",
      "daysAgo": 7,
      "changes": [
        {
          "type": "price",
          "dir": "down",
          "text": "Koers -21.3% deze week ($49\u2192$39)"
        }
      ]
    },
    {
      "ticker": "QBTS",
      "daysAgo": 7,
      "changes": [
        {
          "type": "price",
          "dir": "down",
          "text": "Koers -18.0% deze week ($23\u2192$19)"
        }
      ]
    },
    {
      "ticker": "UBTECH",
      "daysAgo": 7,
      "changes": [
        {
          "type": "price",
          "dir": "down",
          "text": "Koers -21.9% deze week ($109\u2192$85)"
        }
      ]
    },
    {
      "ticker": "SERV",
      "daysAgo": 7,
      "changes": [
        {
          "type": "price",
          "dir": "down",
          "text": "Koers -10.0% deze week ($6\u2192$6)"
        }
      ]
    },
    {
      "ticker": "RR",
      "daysAgo": 7,
      "changes": [
        {
          "type": "price",
          "dir": "down",
          "text": "Koers -22.5% deze week ($2\u2192$2)"
        }
      ]
    },
    {
      "ticker": "TSCO",
      "daysAgo": 3,
      "changes": [
        {
          "type": "rsi",
          "dir": "up",
          "text": "RSI weekly oversold (29)"
        }
      ]
    },
    {
      "ticker": "ODFL",
      "daysAgo": 3,
      "changes": [
        {
          "type": "signal",
          "dir": "up",
          "text": "Signaal: CAUTION (overextended) \u2192 KOOP"
        }
      ]
    }
  ],
  "changedCount": 55,
  "note": "Toont enkel wat veranderde t.o.v. ~7 dagen geleden. Geen wijzigingen = stabiele week."
}